{"swagger":"2.0","info":{},"paths":{"/api/v2/admin/ambassador/forms":{"get":{"produces":["application/json"],"responses":{"200":{"schema":{"items":{"$ref":"#/definitions/ambassador.ChapterForm"},"type":"array"}}},"security":[{}],"summary":"Get all chapter forms"}},"/api/v2/admin/ambassador/institutes":{"get":{"produces":["application/json"],"responses":{"200":{"schema":{"items":{"type":"string"},"type":"array"}}},"security":[{}],"summary":"Get institutes"}},"/api/v2/admin/ambassador/reports/{institute}":{"get":{"parameters":[{"in":"path","name":"institute","required":true,"type":"string"}],"produces":["application/json"],"responses":{"200":{"schema":{"items":{"$ref":"#/definitions/ambassador.WeeklyReport"},"type":"array"}}},"security":[{}],"summary":"Get institute reports"}},"/api/v2/admin/ambassador/tasks":{"post":{"consumes":["application/json"],"parameters":[{"in":"body","name":"body","required":true,"schema":{"$ref":"#/definitions/ambassador.Task"}}],"produces":["application/json"],"responses":{"201":{"schema":{"$ref":"#/definitions/ambassador.Task"}},"400":{"schema":{"$ref":"#/definitions/response.ApiResponse"}}},"security":[{}],"summary":"Create ambassador task"}},"/api/v2/admin/carts":{"get":{"produces":["application/json"],"responses":{"200":{"schema":{"items":{"$ref":"#/definitions/commerce.Cart"},"type":"array"}}},"security":[{}],"summary":"List all carts"}},"/api/v2/admin/health":{"get":{"produces":["application/json"],"responses":{"200":{"schema":{"$ref":"#/definitions/admin.HealthResponse"}}},"security":[{}],"summary":"System health check"}},"/api/v2/admin/notifications/broadcast":{"post":{"consumes":["application/json"],"parameters":[{"in":"body","name":"body","required":true,"schema":{"$ref":"#/definitions/notifications.BroadcastRequest"}}],"produces":["application/json"],"responses":{"200":{"schema":{"additionalProperties":{"type":"string"},"type":"object"}}},"security":[{}],"summary":"Broadcast notification"}},"/api/v2/admin/notifications/tokens/user/{user_id}":{"delete":{"parameters":[{"in":"path","name":"user_id","required":true,"type":"string"}],"produces":["application/json"],"responses":{"200":{"schema":{"additionalProperties":{"type":"string"},"type":"object"}}},"security":[{}],"summary":"Delete user tokens"}},"/api/v2/admin/notifications/tokens/{expo_token}":{"delete":{"parameters":[{"in":"path","name":"expo_token","required":true,"type":"string"}],"produces":["application/json"],"responses":{"200":{"schema":{"additionalProperties":{"type":"string"},"type":"object"}}},"security":[{}],"summary":"Delete specific token"}},"/api/v2/admin/notifications/users/{user_id}/send":{"post":{"consumes":["application/json"],"parameters":[{"in":"path","name":"user_id","required":true,"type":"string"},{"in":"body","name":"body","required":true,"schema":{"$ref":"#/definitions/notifications.SendToUserRequest"}}],"produces":["application/json"],"responses":{"200":{"schema":{"additionalProperties":{"type":"string"},"type":"object"}}},"security":[{}],"summary":"Send notification to user"}},"/api/v2/admin/orders":{"get":{"produces":["application/json"],"responses":{"200":{"schema":{"items":{"$ref":"#/definitions/commerce.Order"},"type":"array"}}},"security":[{}],"summary":"List all orders"}},"/api/v2/admin/orders/{orderID}":{"put":{"consumes":["application/json"],"parameters":[{"in":"path","name":"orderID","required":true,"type":"string"},{"in":"body","name":"body","required":true,"schema":{"$ref":"#/definitions/admin.AdminOrderUpdateRequest"}}],"produces":["application/json"],"responses":{"200":{"schema":{"additionalProperties":{"type":"string"},"type":"object"}}},"security":[{}],"summary":"Update order"}},"/api/v2/admin/otps":{"get":{"produces":["application/json"],"responses":{"200":{"schema":{"items":{"$ref":"#/definitions/identity.User"},"type":"array"}}},"security":[{}],"summary":"Get active OTPs"}},"/api/v2/admin/products-queue":{"get":{"produces":["application/json"],"responses":{"200":{"schema":{"items":{"$ref":"#/definitions/seller.ProductsQueue"},"type":"array"}}},"security":[{}],"summary":"Get products queue"}},"/api/v2/admin/sellers":{"get":{"produces":["application/json"],"responses":{"200":{"schema":{"items":{"$ref":"#/definitions/seller.SellerProfile"},"type":"array"}}},"security":[{}],"summary":"Get all sellers"}},"/api/v2/admin/sellers/{id}":{"get":{"parameters":[{"in":"path","name":"id","required":true,"type":"string"}],"produces":["application/json"],"responses":{"200":{"schema":{"$ref":"#/definitions/seller.SellerProfile"}},"404":{"schema":{"$ref":"#/definitions/response.ApiResponse"}}},"security":[{}],"summary":"Get seller by ID"}},"/api/v2/admin/sellers/{id}/approve":{"put":{"consumes":["application/json"],"parameters":[{"in":"path","name":"id","required":true,"type":"string"},{"in":"body","name":"body","required":true,"schema":{"$ref":"#/definitions/admin.SellerApprovalRequest"}}],"produces":["application/json"],"responses":{"200":{"schema":{"additionalProperties":{"type":"string"},"type":"object"}},"404":{"schema":{"$ref":"#/definitions/response.ApiResponse"}}},"security":[{}],"summary":"Approve or suspend seller"}},"/api/v2/admin/updates":{"post":{"consumes":["application/json"],"parameters":[{"in":"body","name":"body","required":true,"schema":{"$ref":"#/definitions/updates.CreateUpdateRequest"}}],"produces":["application/json"],"responses":{"201":{"schema":{"$ref":"#/definitions/updates.Update"}},"400":{"schema":{"$ref":"#/definitions/response.ApiResponse"}}},"security":[{}],"summary":"Create app update"}},"/api/v2/admin/users":{"get":{"produces":["application/json"],"responses":{"200":{"schema":{"items":{"$ref":"#/definitions/identity.User"},"type":"array"}}},"security":[{}],"summary":"Get all users"}},"/api/v2/admin/waitlist":{"get":{"produces":["application/json"],"responses":{"200":{"schema":{"items":{"$ref":"#/definitions/waitlist.WaitlistEntry"},"type":"array"}}},"security":[{}],"summary":"Get waitlist"}},"/api/v2/ambassador/dashboard":{"get":{"produces":["application/json"],"responses":{"200":{"schema":{"$ref":"#/definitions/ambassador.DashboardResponse"}}},"security":[{}],"summary":"Ambassador dashboard"}},"/api/v2/ambassador/data":{"get":{"parameters":[{"in":"query","name":"phone_number","required":true,"type":"string"}],"produces":["application/json"],"responses":{"200":{"schema":{"$ref":"#/definitions/ambassador.ChapterForm"}},"404":{"schema":{"$ref":"#/definitions/response.ApiResponse"}}},"summary":"Get ambassador data"}},"/api/v2/ambassador/login":{"post":{"consumes":["application/json"],"parameters":[{"in":"body","name":"body","required":true,"schema":{"$ref":"#/definitions/ambassador.LoginRequest"}}],"produces":["application/json"],"responses":{"200":{"schema":{"$ref":"#/definitions/ambassador.LoginResponse"}},"401":{"schema":{"$ref":"#/definitions/response.ApiResponse"}}},"summary":"Ambassador login"}},"/api/v2/ambassador/ranking":{"get":{"produces":["application/json"],"responses":{"200":{"schema":{"items":{"$ref":"#/definitions/ambassador.InstituteRanking"},"type":"array"}}},"summary":"Get institute ranking"}},"/api/v2/ambassador/reports":{"post":{"consumes":["application/json"],"parameters":[{"in":"body","name":"body","required":true,"schema":{"$ref":"#/definitions/ambassador.WeeklyReport"}}],"produces":["application/json"],"responses":{"201":{"schema":{"$ref":"#/definitions/ambassador.WeeklyReport"}},"400":{"schema":{"$ref":"#/definitions/response.ApiResponse"}}},"security":[{}],"summary":"Submit weekly report"}},"/api/v2/ambassador/reports/me":{"get":{"produces":["application/json"],"responses":{"200":{"schema":{"items":{"$ref":"#/definitions/ambassador.WeeklyReport"},"type":"array"}}},"security":[{}],"summary":"Get my reports"}},"/api/v2/ambassador/tasks":{"get":{"produces":["application/json"],"responses":{"200":{"schema":{"items":{"$ref":"#/definitions/ambassador.Task"},"type":"array"}}},"security":[{}],"summary":"Get ambassador tasks"}},"/api/v2/ambassador/team":{"get":{"produces":["application/json"],"responses":{"200":{"schema":{"items":{"$ref":"#/definitions/ambassador.ChapterForm"},"type":"array"}}},"security":[{}],"summary":"Get ambassador team"}},"/api/v2/ambassador/users":{"get":{"produces":["application/json"],"responses":{"200":{"schema":{"items":{"$ref":"#/definitions/ambassador.UserProfile"},"type":"array"}}},"security":[{}],"summary":"Get institute users"}},"/api/v2/auth/change-password":{"post":{"consumes":["application/json"],"parameters":[{"in":"body","name":"body","required":true,"schema":{"$ref":"#/definitions/identity.ChangePasswordRequest"}}],"produces":["application/json"],"responses":{"200":{"schema":{"additionalProperties":{"type":"string"},"type":"object"}},"400":{"schema":{"$ref":"#/definitions/response.ApiResponse"}}},"security":[{}],"summary":"Change password"}},"/api/v2/auth/login":{"post":{"consumes":["application/json"],"parameters":[{"in":"body","name":"body","required":true,"schema":{"$ref":"#/definitions/identity.LoginRequest"}}],"produces":["application/json"],"responses":{"200":{"schema":{"$ref":"#/definitions/identity.AuthResponse"}},"401":{"schema":{"$ref":"#/definitions/response.ApiResponse"}}},"summary":"Login user"}},"/api/v2/auth/refresh":{"post":{"consumes":["application/json"],"parameters":[{"in":"body","name":"body","required":true,"schema":{"$ref":"#/definitions/identity.RefreshTokenRequest"}}],"produces":["application/json"],"responses":{"200":{"schema":{"$ref":"#/definitions/identity.AuthResponse"}},"401":{"schema":{"$ref":"#/definitions/response.ApiResponse"}}},"summary":"Refresh token"}},"/api/v2/auth/register":{"post":{"consumes":["application/json"],"parameters":[{"in":"body","name":"body","required":true,"schema":{"$ref":"#/definitions/identity.RegisterRequest"}}],"produces":["application/json"],"responses":{"201":{"schema":{"$ref":"#/definitions/identity.AuthResponse"}},"400":{"schema":{"$ref":"#/definitions/response.ApiResponse"}}},"summary":"Register user"}},"/api/v2/auth/reset-password":{"post":{"consumes":["application/json"],"parameters":[{"in":"body","name":"body","required":true,"schema":{"$ref":"#/definitions/identity.ResetPasswordRequest"}}],"produces":["application/json"],"responses":{"200":{"schema":{"additionalProperties":{"type":"string"},"type":"object"}},"400":{"schema":{"$ref":"#/definitions/response.ApiResponse"}}},"summary":"Reset password"}},"/api/v2/auth/reset-password/request":{"post":{"consumes":["application/json"],"parameters":[{"in":"body","name":"body","required":true,"schema":{"$ref":"#/definitions/identity.SendOTPRequest"}}],"produces":["application/json"],"responses":{"200":{"schema":{"additionalProperties":{"type":"string"},"type":"object"}},"404":{"schema":{"$ref":"#/definitions/response.ApiResponse"}}},"summary":"Request password reset"}},"/api/v2/auth/send-otp":{"post":{"consumes":["application/json"],"parameters":[{"in":"body","name":"body","required":true,"schema":{"$ref":"#/definitions/identity.SendOTPRequest"}}],"produces":["application/json"],"responses":{"200":{"schema":{"additionalProperties":{"type":"string"},"type":"object"}},"404":{"schema":{"$ref":"#/definitions/response.ApiResponse"}}},"summary":"Send OTP"}},"/api/v2/auth/verify":{"post":{"consumes":["application/json"],"parameters":[{"in":"body","name":"body","required":true,"schema":{"$ref":"#/definitions/identity.VerifyOTPRequest"}}],"produces":["application/json"],"responses":{"200":{"schema":{"additionalProperties":{"type":"string"},"type":"object"}},"400":{"schema":{"$ref":"#/definitions/response.ApiResponse"}}},"summary":"Verify phone"}},"/api/v2/catalog/brands/{id}/stats":{"get":{"consumes":["application/json"],"parameters":[{"in":"path","name":"id","required":true,"type":"string"}],"produces":["application/json"],"responses":{"200":{"schema":{"additionalProperties":true,"type":"object"}},"404":{"schema":{"$ref":"#/definitions/response.ApiResponse"}}},"summary":"Get brand statistics"}},"/api/v2/catalog/products":{"get":{"consumes":["application/json"],"parameters":[{"in":"query","name":"category","type":"string"},{"in":"query","name":"seller_id","type":"string"},{"in":"query","name":"min_price","type":"number"},{"in":"query","name":"max_price","type":"number"},{"in":"query","name":"sort","type":"string"},{"in":"query","name":"order","type":"string"},{"in":"query","name":"page","type":"integer"},{"in":"query","name":"limit","type":"integer"}],"produces":["application/json"],"responses":{"200":{"schema":{"items":{"$ref":"#/definitions/catalog.Product"},"type":"array"}},"500":{"schema":{"$ref":"#/definitions/response.ApiResponse"}}},"summary":"List products"}},"/api/v2/catalog/products/filter":{"post":{"consumes":["application/json"],"parameters":[{"in":"body","name":"filter","required":true,"schema":{"$ref":"#/definitions/catalog.ProductFilter"}}],"produces":["application/json"],"responses":{"200":{"schema":{"items":{"$ref":"#/definitions/catalog.Product"},"type":"array"}},"400":{"schema":{"$ref":"#/definitions/response.ApiResponse"}}},"summary":"Filter products (POST)"}},"/api/v2/catalog/products/filters":{"get":{"consumes":["application/json"],"produces":["application/json"],"responses":{"200":{"schema":{"$ref":"#/definitions/catalog.ProductFiltersResponse"}},"500":{"schema":{"$ref":"#/definitions/response.ApiResponse"}}},"summary":"Get filter options"}},"/api/v2/catalog/products/search":{"get":{"consumes":["application/json"],"parameters":[{"in":"query","name":"keyword","required":true,"type":"string"},{"in":"query","name":"page","type":"integer"},{"in":"query","name":"limit","type":"integer"}],"produces":["application/json"],"responses":{"200":{"schema":{"items":{"$ref":"#/definitions/catalog.Product"},"type":"array"}},"500":{"schema":{"$ref":"#/definitions/response.ApiResponse"}}},"summary":"Search products"}},"/api/v2/catalog/products/{id}":{"get":{"consumes":["application/json"],"parameters":[{"in":"path","name":"id","required":true,"type":"string"}],"produces":["application/json"],"responses":{"200":{"schema":{"$ref":"#/definitions/catalog.Product"}},"404":{"schema":{"$ref":"#/definitions/response.ApiResponse"}}},"summary":"Get product details"}},"/api/v2/catalog/search/autocomplete":{"get":{"consumes":["application/json"],"parameters":[{"in":"query","name":"q","required":true,"type":"string"}],"produces":["application/json"],"responses":{"200":{"schema":{"items":{"type":"string"},"type":"array"}},"500":{"schema":{"$ref":"#/definitions/response.ApiResponse"}}},"summary":"Search autocomplete"}},"/api/v2/catalog/search/trending":{"get":{"consumes":["application/json"],"parameters":[{"in":"query","name":"limit","type":"integer"}],"produces":["application/json"],"responses":{"200":{"schema":{"items":{"$ref":"#/definitions/catalog.SearchTerm"},"type":"array"}},"500":{"schema":{"$ref":"#/definitions/response.ApiResponse"}}},"summary":"Get trending searches"}},"/api/v2/chapter-forms":{"post":{"consumes":["application/json"],"parameters":[{"in":"body","name":"body","required":true,"schema":{"$ref":"#/definitions/ambassador.ChapterForm"}}],"produces":["application/json"],"responses":{"201":{"schema":{"$ref":"#/definitions/ambassador.ChapterForm"}},"400":{"schema":{"$ref":"#/definitions/response.ApiResponse"}}},"summary":"Submit chapter form"}},"/api/v2/chapter-forms/{id}":{"get":{"parameters":[{"in":"path","name":"id","required":true,"type":"string"}],"produces":["application/json"],"responses":{"200":{"schema":{"$ref":"#/definitions/ambassador.ChapterForm"}},"404":{"schema":{"$ref":"#/definitions/response.ApiResponse"}}},"summary":"Get chapter form"}},"/api/v2/commerce/cart":{"get":{"consumes":["application/json"],"produces":["application/json"],"responses":{"200":{"schema":{"$ref":"#/definitions/commerce.Cart"}},"401":{"schema":{"$ref":"#/definitions/response.ApiResponse"}}},"security":[{}],"summary":"Get user cart"},"post":{"consumes":["application/json"],"parameters":[{"in":"body","name":"body","required":true,"schema":{"$ref":"#/definitions/commerce.AddToCartRequest"}}],"produces":["application/json"],"responses":{"200":{"schema":{"$ref":"#/definitions/commerce.Cart"}},"400":{"schema":{"$ref":"#/definitions/response.ApiResponse"}},"404":{"schema":{"$ref":"#/definitions/response.ApiResponse"}}},"security":[{}],"summary":"Add item to cart"}},"/api/v2/commerce/checkout":{"post":{"consumes":["application/json"],"parameters":[{"in":"body","name":"body","required":true,"schema":{"$ref":"#/definitions/commerce.CheckoutRequest"}}],"produces":["application/json"],"responses":{"201":{"schema":{"$ref":"#/definitions/commerce.ParentOrder"}},"400":{"schema":{"$ref":"#/definitions/response.ApiResponse"}}},"security":[{}],"summary":"Process checkout"}},"/api/v2/commerce/orders":{"get":{"consumes":["application/json"],"produces":["application/json"],"responses":{"200":{"schema":{"items":{"$ref":"#/definitions/commerce.Order"},"type":"array"}}},"security":[{}],"summary":"Get user orders"}},"/api/v2/feedback":{"post":{"consumes":["application/json"],"parameters":[{"in":"body","name":"feedback","required":true,"schema":{"$ref":"#/definitions/feedback.CreateRequest"}}],"produces":["application/json"],"responses":{"201":{"schema":{"$ref":"#/definitions/feedback.Feedback"}},"400":{"schema":{"$ref":"#/definitions/response.ApiResponse"}},"401":{"schema":{"$ref":"#/definitions/response.ApiResponse"}}},"security":[{}],"summary":"Submit feedback"}},"/api/v2/location/addresses":{"get":{"consumes":["application/json"],"produces":["application/json"],"responses":{"200":{"schema":{"items":{"$ref":"#/definitions/location.Address"},"type":"array"}}},"security":[{}],"summary":"Get all user addresses"},"post":{"consumes":["application/json"],"parameters":[{"in":"body","name":"body","required":true,"schema":{"$ref":"#/definitions/location.CreateAddressRequest"}}],"produces":["application/json"],"responses":{"201":{"schema":{"$ref":"#/definitions/location.Address"}},"400":{"schema":{"$ref":"#/definitions/response.ApiResponse"}}},"security":[{}],"summary":"Create user address"}},"/api/v2/location/addresses/default":{"get":{"consumes":["application/json"],"produces":["application/json"],"responses":{"200":{"schema":{"$ref":"#/definitions/location.Address"}},"404":{"schema":{"$ref":"#/definitions/response.ApiResponse"}}},"security":[{}],"summary":"Get default address"}},"/api/v2/location/addresses/{id}":{"delete":{"consumes":["application/json"],"parameters":[{"in":"path","name":"id","required":true,"type":"string"}],"produces":["application/json"],"responses":{"200":{"schema":{"additionalProperties":{"type":"string"},"type":"object"}},"404":{"schema":{"$ref":"#/definitions/response.ApiResponse"}}},"security":[{}],"summary":"Delete address"},"get":{"consumes":["application/json"],"parameters":[{"in":"path","name":"id","required":true,"type":"string"}],"produces":["application/json"],"responses":{"200":{"schema":{"$ref":"#/definitions/location.Address"}},"404":{"schema":{"$ref":"#/definitions/response.ApiResponse"}}},"security":[{}],"summary":"Get a specific address"},"put":{"consumes":["application/json"],"parameters":[{"in":"path","name":"id","required":true,"type":"string"},{"in":"body","name":"body","required":true,"schema":{"$ref":"#/definitions/location.CreateAddressRequest"}}],"produces":["application/json"],"responses":{"200":{"schema":{"$ref":"#/definitions/location.Address"}},"400":{"schema":{"$ref":"#/definitions/response.ApiResponse"}},"404":{"schema":{"$ref":"#/definitions/response.ApiResponse"}}},"security":[{}],"summary":"Update address"}},"/api/v2/location/addresses/{id}/default":{"put":{"consumes":["application/json"],"parameters":[{"in":"path","name":"id","required":true,"type":"string"}],"produces":["application/json"],"responses":{"200":{"schema":{"additionalProperties":{"type":"string"},"type":"object"}},"404":{"schema":{"$ref":"#/definitions/response.ApiResponse"}}},"security":[{}],"summary":"Set default address"}},"/api/v2/logistics/fare-estimate":{"post":{"consumes":["application/json"],"parameters":[{"in":"body","name":"body","required":true,"schema":{"$ref":"#/definitions/logistics.FareEstimateRequest"}}],"produces":["application/json"],"responses":{"200":{"schema":{"items":{"$ref":"#/definitions/logistics.DeliveryOption"},"type":"array"}},"400":{"schema":{"$ref":"#/definitions/response.ApiResponse"}}},"summary":"Get shipping fare estimates"}},"/api/v2/me":{"get":{"consumes":["application/json"],"produces":["application/json"],"responses":{"200":{"schema":{"$ref":"#/definitions/identity.User"}},"401":{"schema":{"$ref":"#/definitions/response.ApiResponse"}}},"security":[{}],"summary":"Get current user profile"},"patch":{"consumes":["application/json"],"parameters":[{"in":"body","name":"body","required":true,"schema":{"$ref":"#/definitions/identity.UpdateProfileRequest"}}],"produces":["application/json"],"responses":{"200":{"schema":{"$ref":"#/definitions/identity.User"}},"400":{"schema":{"$ref":"#/definitions/response.ApiResponse"}}},"security":[{}],"summary":"Update profile"}},"/api/v2/me/measurements":{"put":{"consumes":["application/json"],"parameters":[{"in":"body","name":"body","required":true,"schema":{"$ref":"#/definitions/identity.MeasurementProfile"}}],"produces":["application/json"],"responses":{"200":{"schema":{"$ref":"#/definitions/identity.User"}},"400":{"schema":{"$ref":"#/definitions/response.ApiResponse"}}},"security":[{}],"summary":"Update measurements"}},"/api/v2/notifications-seller/register":{"post":{"consumes":["application/json"],"parameters":[{"in":"body","name":"body","required":true,"schema":{"$ref":"#/definitions/notifications.RegisterTokenRequest"}}],"produces":["application/json"],"responses":{"200":{"schema":{"$ref":"#/definitions/notifications.NotificationToken"}},"400":{"schema":{"$ref":"#/definitions/response.ApiResponse"}}},"security":[{}],"summary":"Register seller push token"}},"/api/v2/notifications-seller/unregister":{"post":{"consumes":["application/json"],"parameters":[{"in":"body","name":"body","required":true,"schema":{"$ref":"#/definitions/notifications.UnregisterTokenRequest"}}],"produces":["application/json"],"responses":{"200":{"schema":{"additionalProperties":{"type":"string"},"type":"object"}}},"security":[{}],"summary":"Unregister seller push token"}},"/api/v2/notifications/register":{"post":{"consumes":["application/json"],"parameters":[{"in":"body","name":"body","required":true,"schema":{"$ref":"#/definitions/notifications.RegisterTokenRequest"}}],"produces":["application/json"],"responses":{"200":{"schema":{"$ref":"#/definitions/notifications.NotificationToken"}},"400":{"schema":{"$ref":"#/definitions/response.ApiResponse"}}},"security":[{}],"summary":"Register push token"}},"/api/v2/notifications/unregister":{"post":{"consumes":["application/json"],"parameters":[{"in":"body","name":"body","required":true,"schema":{"$ref":"#/definitions/notifications.UnregisterTokenRequest"}}],"produces":["application/json"],"responses":{"200":{"schema":{"additionalProperties":{"type":"string"},"type":"object"}}},"security":[{}],"summary":"Unregister push token"}},"/api/v2/seller/analytics/inventory":{"get":{"produces":["application/json"],"responses":{"200":{"schema":{"$ref":"#/definitions/seller.InventoryAnalytics"}}},"security":[{}],"summary":"Get inventory analytics"}},"/api/v2/seller/analytics/orders":{"get":{"produces":["application/json"],"responses":{"200":{"schema":{"$ref":"#/definitions/seller.OrderAnalytics"}}},"security":[{}],"summary":"Get order analytics"}},"/api/v2/seller/analytics/product/{productID}":{"get":{"parameters":[{"in":"path","name":"productID","required":true,"type":"string"}],"produces":["application/json"],"responses":{"200":{"schema":{"$ref":"#/definitions/seller.ProductAnalytics"}},"404":{"schema":{"$ref":"#/definitions/response.ApiResponse"}}},"security":[{}],"summary":"Get product analytics"}},"/api/v2/seller/analytics/sales":{"get":{"produces":["application/json"],"responses":{"200":{"schema":{"$ref":"#/definitions/seller.SalesAnalytics"}}},"security":[{}],"summary":"Get sales analytics"}},"/api/v2/seller/auth/login":{"post":{"consumes":["application/json"],"parameters":[{"in":"body","name":"body","required":true,"schema":{"$ref":"#/definitions/seller.SellerLoginRequest"}}],"produces":["application/json"],"responses":{"200":{"schema":{"$ref":"#/definitions/seller.SellerAuthResponse"}},"401":{"schema":{"$ref":"#/definitions/response.ApiResponse"}}},"summary":"Seller login"}},"/api/v2/seller/auth/register":{"post":{"consumes":["application/json"],"parameters":[{"in":"body","name":"body","required":true,"schema":{"$ref":"#/definitions/seller.SellerRegisterRequest"}}],"produces":["application/json"],"responses":{"201":{"schema":{"$ref":"#/definitions/seller.SellerAuthResponse"}},"400":{"schema":{"$ref":"#/definitions/response.ApiResponse"}}},"summary":"Register seller"}},"/api/v2/seller/inventory/bulk-update":{"post":{"consumes":["application/json"],"parameters":[{"in":"body","name":"body","required":true,"schema":{"items":{"$ref":"#/definitions/seller.InventoryBulkUpdate"},"type":"array"}}],"produces":["application/json"],"responses":{"200":{"schema":{"additionalProperties":{"type":"string"},"type":"object"}},"400":{"schema":{"$ref":"#/definitions/response.ApiResponse"}}},"security":[{}],"summary":"Bulk update inventory"}},"/api/v2/seller/inventory/categories":{"get":{"produces":["application/json"],"responses":{"200":{"schema":{"items":{"$ref":"#/definitions/seller.InventoryCategory"},"type":"array"}}},"security":[{}],"summary":"Get inventory categories"}},"/api/v2/seller/inventory/low-stock":{"get":{"parameters":[{"in":"query","name":"threshold","type":"integer"}],"produces":["application/json"],"responses":{"200":{"schema":{"items":{"$ref":"#/definitions/seller.LowStockAlert"},"type":"array"}}},"security":[{}],"summary":"Get low stock items"}},"/api/v2/seller/orders":{"get":{"produces":["application/json"],"responses":{"200":{"schema":{"items":{"$ref":"#/definitions/seller.SellerOrder"},"type":"array"}}},"security":[{}],"summary":"Get seller orders"}},"/api/v2/seller/orders/{id}/fulfill":{"post":{"consumes":["application/json"],"parameters":[{"in":"path","name":"id","required":true,"type":"string"},{"in":"body","name":"body","schema":{"$ref":"#/definitions/seller.FulfillOrderRequest"}}],"produces":["application/json"],"responses":{"200":{"schema":{"additionalProperties":{"type":"string"},"type":"object"}},"404":{"schema":{"$ref":"#/definitions/response.ApiResponse"}}},"security":[{}],"summary":"Fulfill order"}},"/api/v2/seller/orders/{id}/status":{"put":{"consumes":["application/json"],"parameters":[{"in":"path","name":"id","required":true,"type":"string"},{"in":"body","name":"body","required":true,"schema":{"$ref":"#/definitions/seller.UpdateOrderStatusRequest"}}],"produces":["application/json"],"responses":{"200":{"schema":{"additionalProperties":{"type":"string"},"type":"object"}},"400":{"schema":{"$ref":"#/definitions/response.ApiResponse"}}},"security":[{}],"summary":"Update order status"}},"/api/v2/seller/products":{"get":{"consumes":["application/json"],"parameters":[{"in":"query","name":"status","type":"string"}],"produces":["application/json"],"responses":{"200":{"schema":{"items":{"$ref":"#/definitions/catalog.Product"},"type":"array"}},"401":{"schema":{"$ref":"#/definitions/response.ApiResponse"}}},"security":[{}],"summary":"List seller products"},"post":{"consumes":["application/json"],"parameters":[{"in":"body","name":"product","required":true,"schema":{"$ref":"#/definitions/catalog.Product"}}],"produces":["application/json"],"responses":{"201":{"schema":{"$ref":"#/definitions/seller.ProductsQueue"}},"400":{"schema":{"$ref":"#/definitions/response.ApiResponse"}}},"security":[{}],"summary":"Create product"}},"/api/v2/seller/products/{id}":{"delete":{"consumes":["application/json"],"parameters":[{"in":"path","name":"id","required":true,"type":"string"}],"produces":["application/json"],"responses":{"200":{"schema":{"additionalProperties":{"type":"string"},"type":"object"}},"404":{"schema":{"$ref":"#/definitions/response.ApiResponse"}}},"security":[{}],"summary":"Delete product"},"put":{"consumes":["application/json"],"parameters":[{"in":"path","name":"id","required":true,"type":"string"},{"in":"body","name":"product","required":true,"schema":{"$ref":"#/definitions/catalog.Product"}}],"produces":["application/json"],"responses":{"200":{"schema":{"$ref":"#/definitions/catalog.Product"}},"404":{"schema":{"$ref":"#/definitions/response.ApiResponse"}}},"security":[{}],"summary":"Update product"}},"/api/v2/seller/profile":{"get":{"produces":["application/json"],"responses":{"200":{"schema":{"$ref":"#/definitions/seller.SellerProfile"}},"401":{"schema":{"$ref":"#/definitions/response.ApiResponse"}}},"security":[{}],"summary":"Get seller profile"},"patch":{"consumes":["application/json"],"parameters":[{"in":"body","name":"body","required":true,"schema":{"$ref":"#/definitions/seller.UpdateSellerProfileRequest"}}],"produces":["application/json"],"responses":{"200":{"schema":{"$ref":"#/definitions/seller.SellerProfile"}},"400":{"schema":{"$ref":"#/definitions/response.ApiResponse"}}},"security":[{}],"summary":"Update seller profile"}},"/api/v2/seller/queue":{"get":{"consumes":["application/json"],"produces":["application/json"],"responses":{"200":{"schema":{"items":{"$ref":"#/definitions/seller.ProductsQueue"},"type":"array"}}},"security":[{}],"summary":"Get product queue"}},"/api/v2/seller/queue/pending-embeddings":{"get":{"consumes":["application/json"],"produces":["application/json"],"responses":{"200":{"schema":{"items":{"$ref":"#/definitions/seller.ProductsQueue"},"type":"array"}}},"security":[{}],"summary":"Get products pending embeddings"}},"/api/v2/seller/queue/{id}/embeddings":{"post":{"consumes":["application/json"],"parameters":[{"in":"path","name":"id","required":true,"type":"string"},{"in":"body","name":"body","required":true,"schema":{"$ref":"#/definitions/seller.EmbeddingsRequest"}}],"produces":["application/json"],"responses":{"200":{"schema":{"additionalProperties":{"type":"string"},"type":"object"}},"400":{"schema":{"$ref":"#/definitions/response.ApiResponse"}}},"security":[{}],"summary":"Submit product embeddings"}},"/api/v2/seller/queue/{id}/enrich":{"put":{"consumes":["application/json"],"parameters":[{"in":"path","name":"id","required":true,"type":"string"},{"in":"body","name":"body","required":true,"schema":{"$ref":"#/definitions/seller.EnrichmentRequest"}}],"produces":["application/json"],"responses":{"200":{"schema":{"additionalProperties":{"type":"string"},"type":"object"}},"400":{"schema":{"$ref":"#/definitions/response.ApiResponse"}}},"security":[{}],"summary":"Enrich product"}},"/api/v2/seller/queue/{id}/promote":{"post":{"consumes":["application/json"],"parameters":[{"in":"path","name":"id","required":true,"type":"string"}],"produces":["application/json"],"responses":{"200":{"schema":{"additionalProperties":{"type":"string"},"type":"object"}},"400":{"schema":{"$ref":"#/definitions/response.ApiResponse"}}},"security":[{}],"summary":"Promote product"}},"/api/v2/shopify/auth":{"get":{"parameters":[{"in":"query","name":"shop","required":true,"type":"string"}],"produces":["application/json"],"responses":{"400":{"schema":{"$ref":"#/definitions/response.ApiResponse"}}},"security":[{}],"summary":"Connect Shopify store"}},"/api/v2/shopify/callback":{"get":{"parameters":[{"in":"query","name":"code","required":true,"type":"string"},{"in":"query","name":"shop","required":true,"type":"string"},{"in":"query","name":"state","required":true,"type":"string"},{"in":"query","name":"hmac","required":true,"type":"string"}],"produces":["application/json"],"summary":"Shopify OAuth callback"}},"/api/v2/shopify/disconnect":{"delete":{"produces":["application/json"],"responses":{"200":{"schema":{"additionalProperties":{"type":"string"},"type":"object"}}},"security":[{}],"summary":"Disconnect Shopify store"}},"/api/v2/shopify/status":{"get":{"produces":["application/json"],"responses":{"200":{"schema":{"$ref":"#/definitions/shopify.ConnectionStatus"}}},"security":[{}],"summary":"Get Shopify connection status"}},"/api/v2/shopify/sync":{"post":{"produces":["application/json"],"responses":{"200":{"schema":{"$ref":"#/definitions/shopify.SyncResponse"}},"400":{"schema":{"$ref":"#/definitions/response.ApiResponse"}},"404":{"schema":{"$ref":"#/definitions/response.ApiResponse"}}},"security":[{}],"summary":"Sync products from Shopify"}},"/api/v2/social/polls/active":{"get":{"consumes":["application/json"],"produces":["application/json"],"responses":{"200":{"schema":{"$ref":"#/definitions/social.Poll"}},"404":{"schema":{"$ref":"#/definitions/response.ApiResponse"}}},"summary":"Get active poll"}},"/api/v2/social/polls/{id}/vote":{"post":{"consumes":["application/json"],"parameters":[{"in":"path","name":"id","required":true,"type":"string"},{"in":"body","name":"vote","required":true,"schema":{"$ref":"#/definitions/social.VoteRequest"}}],"produces":["application/json"],"responses":{"200":{"schema":{"additionalProperties":{"type":"string"},"type":"object"}},"400":{"schema":{"$ref":"#/definitions/response.ApiResponse"}}},"security":[{}],"summary":"Vote in poll"}},"/api/v2/social/reviews/app":{"post":{"consumes":["application/json"],"parameters":[{"in":"body","name":"review","required":true,"schema":{"$ref":"#/definitions/social.CreateAppReviewRequest"}}],"produces":["application/json"],"responses":{"201":{"schema":{"$ref":"#/definitions/social.AppReview"}},"400":{"schema":{"$ref":"#/definitions/response.ApiResponse"}}},"security":[{}],"summary":"Create app review"}},"/api/v2/social/reviews/app/featured":{"get":{"consumes":["application/json"],"produces":["application/json"],"responses":{"200":{"schema":{"items":{"$ref":"#/definitions/social.AppReview"},"type":"array"}}},"summary":"Get featured app reviews"}},"/api/v2/social/reviews/brand":{"post":{"consumes":["application/json"],"parameters":[{"in":"body","name":"review","required":true,"schema":{"$ref":"#/definitions/social.CreateBrandReviewRequest"}}],"produces":["application/json"],"responses":{"201":{"schema":{"$ref":"#/definitions/social.BrandReview"}},"400":{"schema":{"$ref":"#/definitions/response.ApiResponse"}}},"security":[{}],"summary":"Create brand review"}},"/api/v2/social/reviews/brand/{sellerId}":{"get":{"consumes":["application/json"],"parameters":[{"in":"path","name":"sellerId","required":true,"type":"string"}],"produces":["application/json"],"responses":{"200":{"schema":{"items":{"$ref":"#/definitions/social.BrandReview"},"type":"array"}}},"summary":"Get brand reviews"}},"/api/v2/updates":{"get":{"produces":["application/json"],"responses":{"200":{"schema":{"items":{"$ref":"#/definitions/updates.Update"},"type":"array"}}},"summary":"Get app updates"}},"/api/v2/waitlist":{"post":{"consumes":["application/json"],"parameters":[{"in":"body","name":"body","required":true,"schema":{"$ref":"#/definitions/waitlist.CreateRequest"}}],"produces":["application/json"],"responses":{"201":{"schema":{"$ref":"#/definitions/waitlist.WaitlistEntry"}},"400":{"schema":{"$ref":"#/definitions/response.ApiResponse"}}},"summary":"Join waitlist"}},"/api/v2/waitlist/spots":{"get":{"consumes":["application/json"],"produces":["application/json"],"responses":{"200":{"schema":{"$ref":"#/definitions/waitlist.SpotsResponse"}}},"summary":"Get total waitlist count"}},"/api/v2/waitlist/status":{"get":{"consumes":["application/json"],"parameters":[{"in":"query","name":"phone_number","required":true,"type":"string"}],"produces":["application/json"],"responses":{"200":{"schema":{"$ref":"#/definitions/waitlist.WaitlistEntry"}},"404":{"schema":{"$ref":"#/definitions/response.ApiResponse"}}},"summary":"Check waitlist position"}}},"definitions":{"admin.AdminOrderUpdateRequest":{"properties":{"status":{"type":"string"}},"required":["status"],"type":"object"},"admin.HealthResponse":{"properties":{"services":{"additionalProperties":{"type":"string"},"type":"object"},"status":{"type":"string"},"timestamp":{"type":"string"}},"type":"object"},"admin.SellerApprovalRequest":{"properties":{"approved":{"type":"boolean"},"note":{"type":"string"}},"type":"object"},"ambassador.ChapterForm":{"properties":{"apply_chapter_head":{"type":"boolean"},"chapter_head_motivation":{"type":"string"},"cohort":{"type":"string"},"commitment_hours":{"type":"string"},"created_at":{"type":"string"},"experience_link":{"type":"string"},"final_answer":{"type":"string"},"gender":{"type":"string"},"id":{"type":"string"},"instagram_handle":{"type":"string"},"institute":{"type":"string"},"is_chapter_head":{"type":"boolean"},"motivation":{"type":"integer"},"name":{"type":"string"},"phone":{"type":"string"},"role":{"type":"string"},"secondary_role":{"type":"string"},"year":{"type":"string"}},"type":"object"},"ambassador.DashboardResponse":{"properties":{"ambassador":{"$ref":"#/definitions/ambassador.ChapterForm"},"team_mates":{"items":{"$ref":"#/definitions/ambassador.ChapterForm"},"type":"array"}},"type":"object"},"ambassador.InstituteRanking":{"properties":{"count":{"type":"integer"},"institute":{"type":"string"},"rank":{"type":"integer"}},"type":"object"},"ambassador.LoginRequest":{"properties":{"phone_number":{"type":"string"}},"required":["phone_number"],"type":"object"},"ambassador.LoginResponse":{"properties":{"ambassador":{"$ref":"#/definitions/ambassador.ChapterForm"},"token":{"type":"string"}},"type":"object"},"ambassador.Task":{"properties":{"cohort":{"type":"string"},"created_at":{"type":"string"},"deadline":{"type":"string"},"id":{"type":"string"},"reward_points":{"type":"integer"},"status":{"type":"string"},"target_institute":{"type":"string"},"task_type":{"type":"string"},"title":{"type":"string"},"week_number":{"type":"integer"}},"type":"object"},"ambassador.UserProfile":{"properties":{"age":{"type":"integer"},"avatar":{"type":"string"},"id":{"type":"string"},"name":{"type":"string"},"phone_number":{"type":"string"},"registered_at":{"type":"string"},"swipe_count":{"type":"integer"},"verification_status":{"type":"string"}},"type":"object"},"ambassador.WeeklyReport":{"properties":{"ambassador_id":{"type":"string"},"created_at":{"type":"string"},"id":{"type":"string"},"institute":{"type":"string"},"proof_files":{"items":{"type":"string"},"type":"array"},"reporter_name":{"type":"string"},"tasks_summary":{"type":"string"},"week_number":{"type":"integer"}},"type":"object"},"catalog.Brand":{"properties":{"id":{"type":"string"},"name":{"type":"string"}},"type":"object"},"catalog.Category":{"properties":{"id":{"type":"string"},"name":{"type":"string"},"slug":{"type":"string"}},"type":"object"},"catalog.Inventory":{"properties":{"available_quantity":{"type":"integer"},"in_stock":{"type":"boolean"}},"type":"object"},"catalog.Option":{"properties":{"name":{"type":"string"},"values":{"items":{"type":"string"},"type":"array"}},"type":"object"},"catalog.PriceRange":{"properties":{"max":{"type":"number"},"min":{"type":"number"}},"type":"object"},"catalog.Pricing":{"properties":{"compare_at_price":{"type":"number"},"currency":{"type":"string"},"discount_value":{"type":"number"},"discounted":{"type":"boolean"},"discounted_price":{"type":"number"},"price":{"type":"number"}},"type":"object"},"catalog.Product":{"properties":{"categories":{"items":{"$ref":"#/definitions/catalog.Category"},"type":"array"},"created_at":{"type":"string"},"handle":{"type":"string"},"id":{"type":"string"},"images":{"items":{"type":"string"},"type":"array"},"inventory":{"$ref":"#/definitions/catalog.Inventory"},"is_featured":{"type":"boolean"},"is_trending":{"type":"boolean"},"options":{"items":{"$ref":"#/definitions/catalog.Option"},"type":"array"},"pricing":{"$ref":"#/definitions/catalog.Pricing"},"product_type":{"type":"string"},"published_at":{"type":"string"},"rating":{"type":"number"},"raw_id":{"type":"string"},"review_count":{"type":"integer"},"seller_id":{"type":"string"},"seller_logo":{"type":"string"},"seller_name":{"type":"string"},"shipping_details":{"$ref":"#/definitions/catalog.Shipping"},"short_description":{"type":"string"},"status":{"type":"string"},"tags":{"items":{"type":"string"},"type":"array"},"title":{"type":"string"},"updated_at":{"type":"string"},"variants":{"items":{"$ref":"#/definitions/catalog.Variant"},"type":"array"}},"type":"object"},"catalog.ProductFilter":{"properties":{"category_id":{"type":"string"},"colors":{"items":{"type":"string"},"type":"array"},"keyword":{"type":"string"},"limit":{"type":"string"},"materials":{"items":{"type":"string"},"type":"array"},"max_price":{"type":"string"},"min_price":{"type":"string"},"occasions":{"items":{"type":"string"},"type":"array"},"order":{"type":"string"},"page":{"type":"string"},"product_types":{"items":{"type":"string"},"type":"array"},"seller_id":{"type":"string"},"sizes":{"items":{"type":"string"},"type":"array"},"sort":{"type":"string"},"status":{"type":"string"}},"type":"object"},"catalog.ProductFiltersResponse":{"properties":{"brands":{"items":{"$ref":"#/definitions/catalog.Brand"},"type":"array"},"categories":{"items":{"$ref":"#/definitions/catalog.Category"},"type":"array"},"colors":{"items":{"type":"string"},"type":"array"},"materials":{"items":{"type":"string"},"type":"array"},"occasions":{"items":{"type":"string"},"type":"array"},"price_ranges":{"items":{"$ref":"#/definitions/catalog.PriceRange"},"type":"array"},"product_types":{"items":{"type":"string"},"type":"array"},"sizes":{"items":{"type":"string"},"type":"array"}},"type":"object"},"catalog.SearchTerm":{"properties":{"count":{"type":"integer"},"term":{"type":"string"}},"type":"object"},"catalog.Shipping":{"properties":{"free_shipping":{"type":"boolean"}},"type":"object"},"catalog.Variant":{"properties":{"available":{"type":"boolean"},"id":{"type":"string"},"options":{"additionalProperties":{"type":"string"},"type":"object"},"price":{"type":"number"},"sku":{"type":"string"},"title":{"type":"string"}},"type":"object"},"commerce.AddToCartRequest":{"properties":{"product_id":{"type":"string"},"quantity":{"minimum":1,"type":"integer"},"variant_id":{"type":"string"}},"required":["product_id","quantity","variant_id"],"type":"object"},"commerce.Cart":{"properties":{"created_at":{"type":"string"},"gift_details":{"$ref":"#/definitions/commerce.GiftDetails"},"id":{"type":"string"},"items":{"items":{"$ref":"#/definitions/commerce.CartItem"},"type":"array"},"updated_at":{"type":"string"},"user_id":{"type":"string"}},"type":"object"},"commerce.CartItem":{"properties":{"price":{"type":"number"},"product_id":{"type":"string"},"quantity":{"type":"integer"},"variant_id":{"type":"string"}},"type":"object"},"commerce.CheckoutRequest":{"properties":{"address_id":{"type":"string"},"payment_method":{"type":"string"}},"required":["address_id","payment_method"],"type":"object"},"commerce.GiftDetails":{"properties":{"gift_message":{"type":"string"},"is_gift":{"type":"boolean"},"recipient_name":{"type":"string"},"wrap_gift":{"type":"boolean"}},"type":"object"},"commerce.Order":{"properties":{"created_at":{"type":"string"},"id":{"type":"string"},"order_items":{"items":{"$ref":"#/definitions/commerce.OrderItem"},"type":"array"},"order_number":{"type":"string"},"parent_order_id":{"type":"string"},"seller_id":{"type":"string"},"status":{"$ref":"#/definitions/commerce.OrderStatus"},"total":{"type":"number"},"user_id":{"type":"string"}},"type":"object"},"commerce.OrderItem":{"properties":{"id":{"type":"string"},"product_id":{"type":"string"},"quantity":{"type":"integer"},"unit_price":{"type":"number"},"variant_id":{"type":"string"}},"type":"object"},"commerce.OrderStatus":{"enum":["pending","confirmed","shipped","delivered","cancelled","returned"],"type":"string"},"commerce.ParentOrder":{"properties":{"child_order_ids":{"items":{"type":"string"},"type":"array"},"created_at":{"type":"string"},"id":{"type":"string"},"payment_method":{"type":"string"},"shipping_fee":{"type":"number"},"status":{"type":"string"},"subtotal":{"type":"number"},"total_amount":{"type":"number"},"user_id":{"type":"string"}},"type":"object"},"feedback.CreateRequest":{"properties":{"category":{"type":"string"},"message":{"type":"string"},"screenshot_url":{"type":"string"}},"required":["category","message"],"type":"object"},"feedback.Feedback":{"properties":{"category":{"type":"string"},"created_at":{"type":"string"},"id":{"type":"string"},"message":{"type":"string"},"screenshot_url":{"type":"string"},"status":{"type":"string"},"user_id":{"type":"string"}},"type":"object"},"identity.AuthResponse":{"properties":{"token":{"type":"string"},"user":{"$ref":"#/definitions/identity.User"}},"type":"object"},"identity.ChangePasswordRequest":{"properties":{"new_password":{"minLength":8,"type":"string"},"old_password":{"type":"string"}},"required":["new_password","old_password"],"type":"object"},"identity.LoginRequest":{"properties":{"password":{"type":"string"},"phone_number":{"type":"string"}},"required":["password","phone_number"],"type":"object"},"identity.MeasurementProfile":{"properties":{"bust":{"type":"number"},"height":{"type":"number"},"hip":{"type":"number"},"inseam_length":{"type":"number"},"preferred_fit":{"type":"string"},"shoe_size":{"type":"number"},"shoe_size_system":{"type":"string"},"shoulder":{"type":"number"},"updated_at":{"type":"string"},"waist":{"type":"number"},"weight":{"type":"number"}},"type":"object"},"identity.NotificationPrefs":{"properties":{"email":{"type":"boolean"},"push_notification":{"type":"boolean"},"sms":{"type":"boolean"}},"type":"object"},"identity.RecentlyViewed":{"properties":{"product_id":{"type":"string"},"viewed_at":{"type":"string"}},"type":"object"},"identity.RefreshTokenRequest":{"properties":{"token":{"type":"string"}},"required":["token"],"type":"object"},"identity.RegisterRequest":{"properties":{"email":{"type":"string"},"name":{"type":"string"},"password":{"minLength":8,"type":"string"},"phone_number":{"type":"string"}},"required":["name","password","phone_number"],"type":"object"},"identity.ResetPasswordRequest":{"properties":{"new_password":{"minLength":8,"type":"string"},"otp":{"type":"string"},"phone_number":{"type":"string"}},"required":["new_password","otp","phone_number"],"type":"object"},"identity.SendOTPRequest":{"properties":{"phone_number":{"type":"string"}},"required":["phone_number"],"type":"object"},"identity.UpdateProfileRequest":{"properties":{"avatar":{"type":"string"},"gender":{"type":"string"},"institute":{"type":"string"},"name":{"type":"string"},"preferences":{"$ref":"#/definitions/identity.UserPreferences"}},"type":"object"},"identity.User":{"properties":{"account_status":{"type":"string"},"avatar":{"type":"string"},"created_at":{"type":"string"},"email":{"type":"string"},"gender":{"type":"string"},"id":{"type":"string"},"institute":{"type":"string"},"last_login":{"type":"string"},"measurement_profile":{"$ref":"#/definitions/identity.MeasurementProfile"},"name":{"type":"string"},"notification_prefs":{"$ref":"#/definitions/identity.NotificationPrefs"},"phone_number":{"type":"string"},"preferences":{"$ref":"#/definitions/identity.UserPreferences"},"profile_completion":{"type":"integer"},"recently_viewed":{"items":{"$ref":"#/definitions/identity.RecentlyViewed"},"type":"array"},"referral_code":{"type":"string"},"referred_by":{"type":"string"},"role":{"type":"string"},"updated_at":{"type":"string"},"verification_status":{"type":"string"}},"type":"object"},"identity.UserPreferences":{"properties":{"color_preferences":{"items":{"type":"string"},"type":"array"},"favorite_brands":{"items":{"type":"string"},"type":"array"},"favorite_categories":{"items":{"type":"string"},"type":"array"},"preferred_sizes":{"additionalProperties":{"type":"string"},"type":"object"},"price_range_max":{"type":"number"},"price_range_min":{"type":"number"},"style_preferences":{"items":{"type":"string"},"type":"array"}},"type":"object"},"identity.VerifyOTPRequest":{"properties":{"otp":{"type":"string"},"phone_number":{"type":"string"}},"required":["otp","phone_number"],"type":"object"},"location.Address":{"properties":{"address_line1":{"type":"string"},"address_line2":{"type":"string"},"address_type":{"type":"string"},"city":{"type":"string"},"country":{"type":"string"},"created_at":{"type":"string"},"id":{"type":"string"},"instructions":{"type":"string"},"is_default":{"type":"boolean"},"latitude":{"type":"number"},"longitude":{"type":"number"},"name":{"type":"string"},"phone_number":{"type":"string"},"postal_code":{"type":"string"},"province":{"type":"string"},"updated_at":{"type":"string"},"user_id":{"type":"string"}},"type":"object"},"location.CreateAddressRequest":{"properties":{"address_line1":{"type":"string"},"address_line2":{"type":"string"},"address_type":{"type":"string"},"city":{"type":"string"},"country":{"type":"string"},"instructions":{"type":"string"},"is_default":{"type":"boolean"},"latitude":{"type":"number"},"longitude":{"type":"number"},"name":{"type":"string"},"phone_number":{"type":"string"},"postal_code":{"type":"string"},"province":{"type":"string"}},"required":["address_line1","city","country","name","phone_number","province"],"type":"object"},"logistics.DeliveryOption":{"properties":{"estimated_delivery_time":{"type":"string"},"estimated_fare":{"type":"number"},"name":{"$ref":"#/definitions/logistics.DeliveryPartner"}},"type":"object"},"logistics.DeliveryPartner":{"enum":["Bykea","PostEx"],"type":"string"},"logistics.FareEstimateRequest":{"properties":{"customer_latitude":{"type":"number"},"customer_longitude":{"type":"number"},"seller_id":{"type":"string"}},"required":["customer_latitude","customer_longitude","seller_id"],"type":"object"},"notifications.BroadcastRequest":{"properties":{"body":{"type":"string"},"title":{"type":"string"}},"required":["body","title"],"type":"object"},"notifications.NotificationToken":{"properties":{"created_at":{"type":"string"},"expo_token":{"type":"string"},"id":{"type":"string"},"project_type":{"type":"string"},"updated_at":{"type":"string"},"user_id":{"type":"string"}},"type":"object"},"notifications.RegisterTokenRequest":{"properties":{"expo_token":{"type":"string"},"project_type":{"type":"string"}},"required":["expo_token","project_type"],"type":"object"},"notifications.SendToUserRequest":{"properties":{"body":{"type":"string"},"title":{"type":"string"}},"required":["body","title"],"type":"object"},"notifications.UnregisterTokenRequest":{"properties":{"expo_token":{"type":"string"}},"required":["expo_token"],"type":"object"},"response.ApiError":{"properties":{"code":{"type":"string"},"detail":{"type":"string"},"message":{"type":"string"}},"type":"object"},"response.ApiResponse":{"properties":{"error":{"$ref":"#/definitions/response.ApiError"},"success":{"type":"boolean"}},"type":"object"},"seller.EmbeddingsRequest":{"properties":{"embeddings":{"items":{"type":"number"},"type":"array"}},"type":"object"},"seller.Enrichment":{"properties":{"gender":{"type":"string"},"product_type":{"type":"string"},"sizing_guide":{"additionalProperties":true,"type":"object"}},"type":"object"},"seller.EnrichmentRequest":{"properties":{"gender":{"type":"string"},"product_type":{"type":"string"},"sizing_guide":{"additionalProperties":true,"type":"object"}},"type":"object"},"seller.FulfillOrderRequest":{"properties":{"tracking_number":{"type":"string"}},"type":"object"},"seller.InventoryAnalytics":{"properties":{"in_stock":{"type":"integer"},"low_stock":{"type":"integer"},"out_of_stock":{"type":"integer"},"total_products":{"type":"integer"}},"type":"object"},"seller.InventoryBulkUpdate":{"properties":{"product_id":{"type":"string"},"quantity_change":{"type":"integer"},"reason":{"type":"string"},"variant_id":{"type":"string"}},"type":"object"},"seller.InventoryCategory":{"properties":{"count":{"type":"integer"},"name":{"type":"string"}},"type":"object"},"seller.LowStockAlert":{"properties":{"current_quantity":{"type":"integer"},"product_id":{"type":"string"},"product_name":{"type":"string"},"threshold":{"type":"integer"}},"type":"object"},"seller.OrderAnalytics":{"properties":{"cancelled":{"type":"integer"},"delivered":{"type":"integer"},"pending":{"type":"integer"},"shipped":{"type":"integer"},"total":{"type":"integer"}},"type":"object"},"seller.ProductAnalytics":{"properties":{"product_id":{"type":"string"},"product_name":{"type":"string"},"revenue":{"type":"number"},"total_sold":{"type":"integer"}},"type":"object"},"seller.ProductsQueue":{"properties":{"created_at":{"type":"string"},"embeddings":{"items":{"type":"number"},"type":"array"},"enrichment":{"$ref":"#/definitions/seller.Enrichment"},"errors":{"items":{"type":"string"},"type":"array"},"id":{"type":"string"},"product":{"$ref":"#/definitions/catalog.Product"},"seller_id":{"type":"string"},"shopify_product_id":{"type":"string"},"source":{"type":"string"},"status":{"type":"string"},"updated_at":{"type":"string"}},"type":"object"},"seller.SalesAnalytics":{"properties":{"average_order_value":{"type":"number"},"total_orders":{"type":"integer"},"total_revenue":{"type":"number"}},"type":"object"},"seller.SellerAuthResponse":{"properties":{"seller":{"$ref":"#/definitions/seller.SellerProfile"},"token":{"type":"string"}},"type":"object"},"seller.SellerLoginRequest":{"properties":{"email":{"type":"string"},"password":{"type":"string"}},"type":"object"},"seller.SellerOrder":{"properties":{"created_at":{"type":"string"},"id":{"type":"string"},"items":{"items":{"$ref":"#/definitions/seller.SellerOrderItem"},"type":"array"},"order_number":{"type":"string"},"status":{"type":"string"},"total":{"type":"number"},"user_id":{"type":"string"}},"type":"object"},"seller.SellerOrderItem":{"properties":{"id":{"type":"string"},"product_id":{"type":"string"},"quantity":{"type":"integer"},"unit_price":{"type":"number"},"variant_id":{"type":"string"}},"type":"object"},"seller.SellerProfile":{"properties":{"business_name":{"type":"string"},"created_at":{"type":"string"},"email":{"type":"string"},"id":{"type":"string"},"logo_url":{"type":"string"},"name":{"type":"string"},"phone":{"type":"string"},"status":{"type":"string"},"updated_at":{"type":"string"},"website":{"type":"string"}},"type":"object"},"seller.SellerRegisterRequest":{"properties":{"business_name":{"type":"string"},"email":{"type":"string"},"name":{"type":"string"},"password":{"type":"string"},"phone":{"type":"string"},"website":{"type":"string"}},"type":"object"},"seller.UpdateOrderStatusRequest":{"properties":{"status":{"type":"string"}},"type":"object"},"seller.UpdateSellerProfileRequest":{"properties":{"business_name":{"type":"string"},"logo_url":{"type":"string"},"name":{"type":"string"},"website":{"type":"string"}},"type":"object"},"shopify.ConnectionStatus":{"properties":{"connected":{"type":"boolean"},"installed_at":{"type":"string"},"scopes":{"type":"string"},"shop":{"type":"string"}},"type":"object"},"shopify.SyncResponse":{"properties":{"count":{"type":"integer"},"message":{"type":"string"}},"type":"object"},"social.AppReview":{"properties":{"created_at":{"type":"string"},"id":{"type":"string"},"is_featured":{"type":"boolean"},"rating":{"type":"integer"},"review_text":{"type":"string"},"user_avatar":{"type":"string"},"user_id":{"type":"string"},"user_name":{"type":"string"}},"type":"object"},"social.BrandReview":{"properties":{"created_at":{"type":"string"},"id":{"type":"string"},"images":{"items":{"type":"string"},"type":"array"},"rating":{"type":"integer"},"review_text":{"type":"string"},"seller_id":{"type":"string"},"user_id":{"type":"string"}},"type":"object"},"social.CreateAppReviewRequest":{"properties":{"rating":{"maximum":5,"minimum":1,"type":"integer"},"review_text":{"type":"string"}},"required":["rating","review_text"],"type":"object"},"social.CreateBrandReviewRequest":{"properties":{"images":{"items":{"type":"string"},"type":"array"},"rating":{"maximum":5,"minimum":1,"type":"integer"},"review_text":{"type":"string"},"seller_id":{"type":"string"}},"required":["rating","seller_id"],"type":"object"},"social.Poll":{"properties":{"expires_at":{"type":"string"},"id":{"type":"string"},"is_active":{"type":"boolean"},"options":{"items":{"$ref":"#/definitions/social.PollOption"},"type":"array"},"question":{"type":"string"}},"type":"object"},"social.PollOption":{"properties":{"id":{"type":"string"},"text":{"type":"string"},"votes":{"type":"integer"}},"type":"object"},"social.VoteRequest":{"properties":{"option_id":{"type":"string"}},"required":["option_id"],"type":"object"},"updates.CreateUpdateRequest":{"properties":{"body":{"type":"string"},"date":{"type":"string"},"headline":{"type":"string"},"image":{"type":"string"},"subtitle":{"type":"string"}},"required":["body","date","headline"],"type":"object"},"updates.Update":{"properties":{"body":{"type":"string"},"created_at":{"type":"string"},"date":{"type":"string"},"headline":{"type":"string"},"id":{"type":"string"},"image":{"type":"string"},"subtitle":{"type":"string"},"updated_at":{"type":"string"}},"type":"object"},"waitlist.CreateRequest":{"properties":{"institute":{"type":"string"},"name":{"type":"string"},"phone_number":{"type":"string"}},"type":"object"},"waitlist.SpotsResponse":{"properties":{"spots":{"type":"integer"}},"type":"object"},"waitlist.WaitlistEntry":{"properties":{"created_at":{"type":"string"},"id":{"type":"string"},"institute":{"type":"string"},"name":{"type":"string"},"phone_number":{"type":"string"},"spot":{"type":"integer"}},"type":"object"}}}